zyh/__init__.py
zyh/setup_test.py
zyh/utils/__init__.py
zyh/utils/pre_process.py
zyh-0.0.2.data/scripts/setup_test.py
zyh-0.0.2.dist-info/METADATA
zyh-0.0.2.dist-info/WHEEL
zyh-0.0.2.dist-info/entry_points.txt
zyh-0.0.2.dist-info/top_level.txt
zyh-0.0.2.dist-info/RECORD
