Metadata-Version: 2.1
Name: zyh
Version: 0.0.2
Summary: Easily show off amazing scripys by zyh
Home-page: https://github.com/amanyara/zyh
Author: zhangyuhan
Author-email: yhanzh0608@gmail.com
License: MIT
Keywords: python,nlp,show off
Classifier: Development Status :: 3 - Alpha
Classifier: Intended Audience :: Developers
Classifier: Programming Language :: Python :: 3
Classifier: Operating System :: Microsoft :: Windows
Requires-Dist: transformers
Requires-Dist: datasets
Requires-Dist: evaluate
Requires-Dist: peft
Requires-Dist: accelerate
Requires-Dist: gradio
Requires-Dist: optimum
Requires-Dist: sentencepiece
Requires-Dist: scikit-learn
Requires-Dist: pandas
Requires-Dist: matplotlib
Requires-Dist: tensorboard
Requires-Dist: rouge
Requires-Dist: nltk
Requires-Dist: jupyterlab
